CopyFilesHind/__init__.py
CopyFilesHind-1.0.0.dist-info/METADATA
CopyFilesHind-1.0.0.dist-info/WHEEL
CopyFilesHind-1.0.0.dist-info/top_level.txt
CopyFilesHind-1.0.0.dist-info/RECORD
